__init__.py
mispotx/__init__.py
mispotx/cli.py
mispotx/config.ini
mispotx/utils.py
mispotx-1.2.4.dist-info/licenses/LICENSE
mispotx-1.2.4.dist-info/METADATA
mispotx-1.2.4.dist-info/WHEEL
mispotx-1.2.4.dist-info/entry_points.txt
mispotx-1.2.4.dist-info/top_level.txt
mispotx-1.2.4.dist-info/RECORD
